<?xml version="1.0" encoding="UTF-8"?>
<!DOCTYPE suite SYSTEM "http://testng.org/testng-1.0.dtd">
<suite name="Regression">
  <test thread-count="5" name="Test">
    <classes>
      <class name="TestNGconcepts.GoogleApplication"/>
      <class name="TestNGconcepts.Login"/>
      <class name="TestNGconcepts.DisplayPersonalDetails"/>
      <class name="TestNGconcepts.SurveryMonkeyLogin"/>
      <class name="TestNGconcepts.VerifyGoogleApplication"/>
      <class name="TestNGconcepts.FirstTestNGcode"/>
    </classes>
  </test> <!-- Test -->
</suite> <!-- Regression -->
